README.rst
mysqlLink.py
setup.py
mysqlLink.egg-info/PKG-INFO
mysqlLink.egg-info/SOURCES.txt
mysqlLink.egg-info/dependency_links.txt
mysqlLink.egg-info/requires.txt
mysqlLink.egg-info/top_level.txt