Metadata-Version: 1.0
Name: mysqlLink
Version: 1.3
Summary: a tool for linking mysql with python3.6, base on module pymysql
Home-page: https://github.com/DawnAzrael/MysqlTools.git
Author: Azrael
Author-email: yinyuhang1996@gmail.com
License: None
Platform: python3 or later
